myutils/__init__.py
myutils/utils.py
myutils_sat63k/__init__.py
myutils_sat63k/utils.py
myutils_sat63k-0.1.dist-info/METADATA
myutils_sat63k-0.1.dist-info/WHEEL
myutils_sat63k-0.1.dist-info/top_level.txt
myutils_sat63k-0.1.dist-info/RECORD
