Metadata-Version: 2.1
Name: myutils-sat63k
Version: 0.1
Summary: Various utility functions
Requires-Python: >=3.7
